{
  "logs": [
    {
      "id": 1,
      "message": "Installed new network cable on Workstation 005",
      "attention": false,
      "tech": "John",
      "date": "2020-08-01T13:05:10.277Z"
    },
    {
      "message": "Fix HD ON WORKSTATION 009",
      "attention": false,
      "tech": "Sara",
      "date": "2020-08-01T12:02:06.238Z",
      "id": 2
    }
  ],
  "techs": [
    {
      "id": 1,
      "firstName": "Sam",
      "lastname": "Diaz"
    },
    {
      "id": 2,
      "firstName": "Geovany",
      "lastname": "Martinez"
    }
  ]
}